fountain_life_service_clients/__init__.py
fountain_life_service_clients/_base_client.py
fountain_life_service_clients/account_service.py
fountain_life_service_clients/account_service_policy_attributes.py
fountain_life_service_clients/agents_api_service.py
fountain_life_service_clients/ai_template_service.py
fountain_life_service_clients/claimed_domains_service.py
fountain_life_service_clients/cohorts_service.py
fountain_life_service_clients/ehr_ingestion_wearables_api.py
fountain_life_service_clients/ehr_service.py
fountain_life_service_clients/elation_integration_messaging.py
fountain_life_service_clients/email_service_email.py
fountain_life_service_clients/email_service_sms.py
fountain_life_service_clients/fhir_post_processor_service.py
fountain_life_service_clients/fhir_search_service.py
fountain_life_service_clients/file_service.py
fountain_life_service_clients/forum_service.py
fountain_life_service_clients/ga4gh_service.py
fountain_life_service_clients/genomic_ingestion_service.py
fountain_life_service_clients/genomics_report_service.py
fountain_life_service_clients/genomics_service.py
fountain_life_service_clients/invitation_service.py
fountain_life_service_clients/medical_results_service_results.py
fountain_life_service_clients/member_notification_service.py
fountain_life_service_clients/member_operations_service_members.py
fountain_life_service_clients/member_scheduling_service_scheduling_prompts.py
fountain_life_service_clients/oauth_apps_service.py
fountain_life_service_clients/patient_service.py
fountain_life_service_clients/rules_service.py
fountain_life_service_clients/scheduler_service.py
fountain_life_service_clients/streaming_service.py
fountain_life_service_clients/survey_service.py
fountain_life_service_clients/test_service.py
fountain_life_service_clients/user_service.py
fountain_life_service_clients/voice_agents_service.py
fountain_life_service_clients-3.55.0.dist-info/METADATA
fountain_life_service_clients-3.55.0.dist-info/WHEEL
fountain_life_service_clients-3.55.0.dist-info/RECORD
