Metadata-Version: 2.4
Name: fountain-life-service-clients
Version: 3.55.0
Summary: 
License: UNLICENSED
Author: Fountain Life
Author-email: dev@fountainlife.com
Requires-Python: >=3.13,<4.0
Classifier: License :: Other/Proprietary License
Classifier: Programming Language :: Python :: 3
Classifier: Programming Language :: Python :: 3.13
Classifier: Programming Language :: Python :: 3.14
Requires-Dist: lifeomic-chatbot-tools[aws] (>=9.0.1,<10.0.0)
Requires-Dist: pytest-mock (>=3.15.0,<4.0.0)
